setup.py
kin/__init__.py
kin/wu.py
kin/wy.py
kinn.egg-info/PKG-INFO
kinn.egg-info/SOURCES.txt
kinn.egg-info/dependency_links.txt
kinn.egg-info/top_level.txt