Metadata-Version: 1.2
Name: kinn
Version: 0.0.0
Summary: A daily useful kit by KIN.
Home-page: https://github.com/githubuser/kin.git
Author: KIN
License: MIT
Platform: UNKNOWN
Requires-Python: >=3.6.0
